[
  {
    "ContainingType": "LibrarySystemApi.Controllers.AuthorController",
    "Method": "GetAuthors",
    "RelativePath": "api/Author",
    "HttpMethod": "GET",
    "IsController": true,
    "Order": 0,
    "Parameters": [],
    "ReturnTypes": [
      {
        "Type": "System.Collections.Generic.List\u00601[[LibrarySystemApi.Models.Author, LibrarySystemApi, Version=1.0.0.0, Culture=neutral, PublicKeyToken=null]]",
        "MediaTypes": [
          "text/plain",
          "application/json",
          "text/json"
        ],
        "StatusCode": 200
      }
    ]
  },
  {
    "ContainingType": "LibrarySystemApi.Controllers.AuthorController",
    "Method": "AddAuthor",
    "RelativePath": "api/Author",
    "HttpMethod": "POST",
    "IsController": true,
    "Order": 0,
    "Parameters": [
      {
        "Name": "newAuthor",
        "Type": "LibrarySystemApi.Models.Author",
        "IsRequired": true
      }
    ],
    "ReturnTypes": []
  },
  {
    "ContainingType": "LibrarySystemApi.Controllers.AuthorController",
    "Method": "GetAuthorById",
    "RelativePath": "api/Author/{id}",
    "HttpMethod": "GET",
    "IsController": true,
    "Order": 0,
    "Parameters": [
      {
        "Name": "id",
        "Type": "System.Int32",
        "IsRequired": true
      }
    ],
    "ReturnTypes": []
  },
  {
    "ContainingType": "LibrarySystemApi.Controllers.AuthorController",
    "Method": "UpdateAuthor",
    "RelativePath": "api/Author/{id}",
    "HttpMethod": "PUT",
    "IsController": true,
    "Order": 0,
    "Parameters": [
      {
        "Name": "id",
        "Type": "System.Int32",
        "IsRequired": true
      },
      {
        "Name": "newAuthor",
        "Type": "LibrarySystemApi.Models.Author",
        "IsRequired": true
      }
    ],
    "ReturnTypes": []
  },
  {
    "ContainingType": "LibrarySystemApi.Controllers.AuthorController",
    "Method": "DeleteAuthor",
    "RelativePath": "api/Author/{id}",
    "HttpMethod": "DELETE",
    "IsController": true,
    "Order": 0,
    "Parameters": [
      {
        "Name": "id",
        "Type": "System.Int32",
        "IsRequired": true
      }
    ],
    "ReturnTypes": []
  },
  {
    "ContainingType": "LibrarySystemApi.Controllers.BookCopyController",
    "Method": "GetBookCopies",
    "RelativePath": "api/BookCopy",
    "HttpMethod": "GET",
    "IsController": true,
    "Order": 0,
    "Parameters": [],
    "ReturnTypes": [
      {
        "Type": "System.Collections.Generic.List\u00601[[LibrarySystemApi.Models.BookCopy, LibrarySystemApi, Version=1.0.0.0, Culture=neutral, PublicKeyToken=null]]",
        "MediaTypes": [
          "text/plain",
          "application/json",
          "text/json"
        ],
        "StatusCode": 200
      }
    ]
  },
  {
    "ContainingType": "LibrarySystemApi.Controllers.BookCopyController",
    "Method": "AddBookCopy",
    "RelativePath": "api/BookCopy",
    "HttpMethod": "POST",
    "IsController": true,
    "Order": 0,
    "Parameters": [
      {
        "Name": "bookCopyDto",
        "Type": "LibrarySystemApi.Dtos.CreateBookCopyDto",
        "IsRequired": true
      }
    ],
    "ReturnTypes": []
  },
  {
    "ContainingType": "LibrarySystemApi.Controllers.BookCopyController",
    "Method": "GetBookCopyById",
    "RelativePath": "api/BookCopy/{id}",
    "HttpMethod": "GET",
    "IsController": true,
    "Order": 0,
    "Parameters": [
      {
        "Name": "id",
        "Type": "System.Int32",
        "IsRequired": true
      }
    ],
    "ReturnTypes": [
      {
        "Type": "LibrarySystemApi.Models.BookCopy",
        "MediaTypes": [
          "text/plain",
          "application/json",
          "text/json"
        ],
        "StatusCode": 200
      }
    ]
  },
  {
    "ContainingType": "LibrarySystemApi.Controllers.BookCopyController",
    "Method": "UpdateBookCopy",
    "RelativePath": "api/BookCopy/{id}",
    "HttpMethod": "PUT",
    "IsController": true,
    "Order": 0,
    "Parameters": [
      {
        "Name": "id",
        "Type": "System.Int32",
        "IsRequired": true
      },
      {
        "Name": "updatedBookCopyDto",
        "Type": "LibrarySystemApi.Dtos.CreateBookCopyDto",
        "IsRequired": true
      }
    ],
    "ReturnTypes": []
  },
  {
    "ContainingType": "LibrarySystemApi.Controllers.BookCopyController",
    "Method": "DeleteBookCopy",
    "RelativePath": "api/BookCopy/{id}",
    "HttpMethod": "DELETE",
    "IsController": true,
    "Order": 0,
    "Parameters": [
      {
        "Name": "id",
        "Type": "System.Int32",
        "IsRequired": true
      }
    ],
    "ReturnTypes": []
  },
  {
    "ContainingType": "LibrarySystemApi.Controllers.BookLibraryController",
    "Method": "GetLibraryBooks",
    "RelativePath": "api/BookLibrary",
    "HttpMethod": "GET",
    "IsController": true,
    "Order": 0,
    "Parameters": [],
    "ReturnTypes": [
      {
        "Type": "System.Collections.Generic.List\u00601[[LibrarySystemApi.Dtos.BookDto, LibrarySystemApi, Version=1.0.0.0, Culture=neutral, PublicKeyToken=null]]",
        "MediaTypes": [
          "text/plain",
          "application/json",
          "text/json"
        ],
        "StatusCode": 200
      }
    ]
  },
  {
    "ContainingType": "LibrarySystemApi.Controllers.BookLibraryController",
    "Method": "AddBook",
    "RelativePath": "api/BookLibrary",
    "HttpMethod": "POST",
    "IsController": true,
    "Order": 0,
    "Parameters": [
      {
        "Name": "newBookDto",
        "Type": "LibrarySystemApi.Dtos.CreateBookDto",
        "IsRequired": true
      }
    ],
    "ReturnTypes": []
  },
  {
    "ContainingType": "LibrarySystemApi.Controllers.BookLibraryController",
    "Method": "GetBookById",
    "RelativePath": "api/BookLibrary/{id}",
    "HttpMethod": "GET",
    "IsController": true,
    "Order": 0,
    "Parameters": [
      {
        "Name": "id",
        "Type": "System.Int32",
        "IsRequired": true
      }
    ],
    "ReturnTypes": [
      {
        "Type": "LibrarySystemApi.Dtos.BookDto",
        "MediaTypes": [
          "text/plain",
          "application/json",
          "text/json"
        ],
        "StatusCode": 200
      }
    ]
  },
  {
    "ContainingType": "LibrarySystemApi.Controllers.BookLibraryController",
    "Method": "UpdateBook",
    "RelativePath": "api/BookLibrary/{id}",
    "HttpMethod": "PUT",
    "IsController": true,
    "Order": 0,
    "Parameters": [
      {
        "Name": "id",
        "Type": "System.Int32",
        "IsRequired": true
      },
      {
        "Name": "updatedBookDto",
        "Type": "LibrarySystemApi.Dtos.UpdateBookDto",
        "IsRequired": true
      }
    ],
    "ReturnTypes": []
  },
  {
    "ContainingType": "LibrarySystemApi.Controllers.BookLibraryController",
    "Method": "DeleteBook",
    "RelativePath": "api/BookLibrary/{id}",
    "HttpMethod": "DELETE",
    "IsController": true,
    "Order": 0,
    "Parameters": [
      {
        "Name": "id",
        "Type": "System.Int32",
        "IsRequired": true
      }
    ],
    "ReturnTypes": []
  },
  {
    "ContainingType": "LibrarySystemApi.Controllers.BookLibraryController",
    "Method": "GetBooksOrderedByYear",
    "RelativePath": "api/BookLibrary/Order-by-year",
    "HttpMethod": "GET",
    "IsController": true,
    "Order": 0,
    "Parameters": [],
    "ReturnTypes": [
      {
        "Type": "System.Collections.Generic.List\u00601[[LibrarySystemApi.Dtos.BookDto, LibrarySystemApi, Version=1.0.0.0, Culture=neutral, PublicKeyToken=null]]",
        "MediaTypes": [
          "text/plain",
          "application/json",
          "text/json"
        ],
        "StatusCode": 200
      }
    ]
  },
  {
    "ContainingType": "LibrarySystemApi.Controllers.BookLibraryController",
    "Method": "GetBooksByPublicationYear",
    "RelativePath": "api/BookLibrary/publicationYear",
    "HttpMethod": "GET",
    "IsController": true,
    "Order": 0,
    "Parameters": [
      {
        "Name": "year",
        "Type": "System.Int32",
        "IsRequired": false
      }
    ],
    "ReturnTypes": [
      {
        "Type": "System.Collections.Generic.List\u00601[[LibrarySystemApi.Dtos.BookDto, LibrarySystemApi, Version=1.0.0.0, Culture=neutral, PublicKeyToken=null]]",
        "MediaTypes": [
          "text/plain",
          "application/json",
          "text/json"
        ],
        "StatusCode": 200
      }
    ]
  },
  {
    "ContainingType": "LibrarySystemApi.Controllers.BookLibraryController",
    "Method": "SearchBookByTitle",
    "RelativePath": "api/BookLibrary/Search",
    "HttpMethod": "GET",
    "IsController": true,
    "Order": 0,
    "Parameters": [
      {
        "Name": "term",
        "Type": "System.String",
        "IsRequired": false
      }
    ],
    "ReturnTypes": [
      {
        "Type": "System.Collections.Generic.List\u00601[[LibrarySystemApi.Dtos.BookDto, LibrarySystemApi, Version=1.0.0.0, Culture=neutral, PublicKeyToken=null]]",
        "MediaTypes": [
          "text/plain",
          "application/json",
          "text/json"
        ],
        "StatusCode": 200
      }
    ]
  },
  {
    "ContainingType": "LibrarySystemApi.Controllers.GenreController",
    "Method": "GetGenres",
    "RelativePath": "api/Genre",
    "HttpMethod": "GET",
    "IsController": true,
    "Order": 0,
    "Parameters": [],
    "ReturnTypes": [
      {
        "Type": "System.Collections.Generic.List\u00601[[LibrarySystemApi.Models.Genre, LibrarySystemApi, Version=1.0.0.0, Culture=neutral, PublicKeyToken=null]]",
        "MediaTypes": [
          "text/plain",
          "application/json",
          "text/json"
        ],
        "StatusCode": 200
      }
    ]
  },
  {
    "ContainingType": "LibrarySystemApi.Controllers.LoanController",
    "Method": "GetLoand",
    "RelativePath": "api/Loan",
    "HttpMethod": "GET",
    "IsController": true,
    "Order": 0,
    "Parameters": [],
    "ReturnTypes": [
      {
        "Type": "System.Collections.Generic.List\u00601[[LibrarySystemApi.Dtos.LoanDto, LibrarySystemApi, Version=1.0.0.0, Culture=neutral, PublicKeyToken=null]]",
        "MediaTypes": [
          "text/plain",
          "application/json",
          "text/json"
        ],
        "StatusCode": 200
      }
    ]
  },
  {
    "ContainingType": "LibrarySystemApi.Controllers.LoanController",
    "Method": "AddLoan",
    "RelativePath": "api/Loan",
    "HttpMethod": "POST",
    "IsController": true,
    "Order": 0,
    "Parameters": [
      {
        "Name": "newLoanDto",
        "Type": "LibrarySystemApi.Dtos.CreateLoanDto",
        "IsRequired": true
      }
    ],
    "ReturnTypes": []
  },
  {
    "ContainingType": "LibrarySystemApi.Controllers.LoanController",
    "Method": "GetLoanById",
    "RelativePath": "api/Loan/{id}",
    "HttpMethod": "GET",
    "IsController": true,
    "Order": 0,
    "Parameters": [
      {
        "Name": "id",
        "Type": "System.Int32",
        "IsRequired": true
      }
    ],
    "ReturnTypes": [
      {
        "Type": "LibrarySystemApi.Dtos.LoanDto",
        "MediaTypes": [
          "text/plain",
          "application/json",
          "text/json"
        ],
        "StatusCode": 200
      }
    ]
  },
  {
    "ContainingType": "LibrarySystemApi.Controllers.LoanController",
    "Method": "UpdateLoan",
    "RelativePath": "api/Loan/{id}",
    "HttpMethod": "PUT",
    "IsController": true,
    "Order": 0,
    "Parameters": [
      {
        "Name": "id",
        "Type": "System.Int32",
        "IsRequired": true
      },
      {
        "Name": "updatedLoandDto",
        "Type": "LibrarySystemApi.Dtos.CreateLoanDto",
        "IsRequired": true
      }
    ],
    "ReturnTypes": []
  },
  {
    "ContainingType": "LibrarySystemApi.Controllers.LoanController",
    "Method": "DeleteLoan",
    "RelativePath": "api/Loan/{id}",
    "HttpMethod": "DELETE",
    "IsController": true,
    "Order": 0,
    "Parameters": [
      {
        "Name": "id",
        "Type": "System.Int32",
        "IsRequired": true
      }
    ],
    "ReturnTypes": []
  },
  {
    "ContainingType": "LibrarySystemApi.Controllers.LoanController",
    "Method": "RenewLoan",
    "RelativePath": "api/Loan/{id}/renewLoan",
    "HttpMethod": "PUT",
    "IsController": true,
    "Order": 0,
    "Parameters": [
      {
        "Name": "id",
        "Type": "System.Int32",
        "IsRequired": true
      },
      {
        "Name": "renewDto",
        "Type": "LibrarySystemApi.Dtos.RenewLoanDto",
        "IsRequired": true
      }
    ],
    "ReturnTypes": []
  },
  {
    "ContainingType": "LibrarySystemApi.Controllers.LoanController",
    "Method": "CheckoutFromHold",
    "RelativePath": "api/Loan/checkout/{reservationId}",
    "HttpMethod": "POST",
    "IsController": true,
    "Order": 0,
    "Parameters": [
      {
        "Name": "reservationId",
        "Type": "System.Int32",
        "IsRequired": true
      }
    ],
    "ReturnTypes": []
  },
  {
    "ContainingType": "LibrarySystemApi.Controllers.LoanController",
    "Method": "GetOverDueLoans",
    "RelativePath": "api/Loan/overdue-loans",
    "HttpMethod": "GET",
    "IsController": true,
    "Order": 0,
    "Parameters": [],
    "ReturnTypes": [
      {
        "Type": "System.Collections.Generic.List\u00601[[LibrarySystemApi.Dtos.LoanDto, LibrarySystemApi, Version=1.0.0.0, Culture=neutral, PublicKeyToken=null]]",
        "MediaTypes": [
          "text/plain",
          "application/json",
          "text/json"
        ],
        "StatusCode": 200
      }
    ]
  },
  {
    "ContainingType": "LibrarySystemApi.Controllers.LoanController",
    "Method": "ReturnBook",
    "RelativePath": "api/Loan/return",
    "HttpMethod": "POST",
    "IsController": true,
    "Order": 0,
    "Parameters": [
      {
        "Name": "returnDto",
        "Type": "LibrarySystemApi.Dtos.ReturnBookDto",
        "IsRequired": true
      }
    ],
    "ReturnTypes": []
  },
  {
    "ContainingType": "LibrarySystemApi.Controllers.MemberController",
    "Method": "GetMembers",
    "RelativePath": "api/Member",
    "HttpMethod": "GET",
    "IsController": true,
    "Order": 0,
    "Parameters": [],
    "ReturnTypes": [
      {
        "Type": "System.Collections.Generic.List\u00601[[LibrarySystemApi.Models.Member, LibrarySystemApi, Version=1.0.0.0, Culture=neutral, PublicKeyToken=null]]",
        "MediaTypes": [
          "text/plain",
          "application/json",
          "text/json"
        ],
        "StatusCode": 200
      }
    ]
  },
  {
    "ContainingType": "LibrarySystemApi.Controllers.MemberController",
    "Method": "AddMembers",
    "RelativePath": "api/Member",
    "HttpMethod": "POST",
    "IsController": true,
    "Order": 0,
    "Parameters": [
      {
        "Name": "newMemberDto",
        "Type": "LibrarySystemApi.Dtos.CreateMemberDto",
        "IsRequired": true
      }
    ],
    "ReturnTypes": []
  },
  {
    "ContainingType": "LibrarySystemApi.Controllers.MemberController",
    "Method": "GetMemberById",
    "RelativePath": "api/Member/{id}",
    "HttpMethod": "GET",
    "IsController": true,
    "Order": 0,
    "Parameters": [
      {
        "Name": "id",
        "Type": "System.Int32",
        "IsRequired": true
      }
    ],
    "ReturnTypes": []
  },
  {
    "ContainingType": "LibrarySystemApi.Controllers.MemberController",
    "Method": "UpdateMember",
    "RelativePath": "api/Member/{id}",
    "HttpMethod": "PUT",
    "IsController": true,
    "Order": 0,
    "Parameters": [
      {
        "Name": "id",
        "Type": "System.Int32",
        "IsRequired": true
      },
      {
        "Name": "updatedMemberDto",
        "Type": "LibrarySystemApi.Dtos.UpdateMemberDto",
        "IsRequired": true
      }
    ],
    "ReturnTypes": []
  },
  {
    "ContainingType": "LibrarySystemApi.Controllers.MemberController",
    "Method": "DeleteMember",
    "RelativePath": "api/Member/{id}",
    "HttpMethod": "DELETE",
    "IsController": true,
    "Order": 0,
    "Parameters": [
      {
        "Name": "id",
        "Type": "System.Int32",
        "IsRequired": true
      }
    ],
    "ReturnTypes": []
  },
  {
    "ContainingType": "LibrarySystemApi.Controllers.MemberController",
    "Method": "GetBorrowedBooksForMember",
    "RelativePath": "api/Member/{id}/borrowHistory",
    "HttpMethod": "GET",
    "IsController": true,
    "Order": 0,
    "Parameters": [
      {
        "Name": "id",
        "Type": "System.Int32",
        "IsRequired": true
      }
    ],
    "ReturnTypes": [
      {
        "Type": "System.Collections.Generic.List\u00601[[LibrarySystemApi.Dtos.LoanDto, LibrarySystemApi, Version=1.0.0.0, Culture=neutral, PublicKeyToken=null]]",
        "MediaTypes": [
          "text/plain",
          "application/json",
          "text/json"
        ],
        "StatusCode": 200
      }
    ]
  },
  {
    "ContainingType": "LibrarySystemApi.Controllers.ReservationController",
    "Method": "GetReservations",
    "RelativePath": "api/Reservation",
    "HttpMethod": "GET",
    "IsController": true,
    "Order": 0,
    "Parameters": [],
    "ReturnTypes": [
      {
        "Type": "System.Collections.Generic.List\u00601[[LibrarySystemApi.Models.Reservation, LibrarySystemApi, Version=1.0.0.0, Culture=neutral, PublicKeyToken=null]]",
        "MediaTypes": [
          "text/plain",
          "application/json",
          "text/json"
        ],
        "StatusCode": 200
      }
    ]
  },
  {
    "ContainingType": "LibrarySystemApi.Controllers.ReservationController",
    "Method": "AddReservation",
    "RelativePath": "api/Reservation",
    "HttpMethod": "POST",
    "IsController": true,
    "Order": 0,
    "Parameters": [
      {
        "Name": "newReservation",
        "Type": "LibrarySystemApi.Dtos.CreateReservationDto",
        "IsRequired": true
      }
    ],
    "ReturnTypes": []
  },
  {
    "ContainingType": "LibrarySystemApi.Controllers.ReservationController",
    "Method": "GetReservationById",
    "RelativePath": "api/Reservation/{id}",
    "HttpMethod": "GET",
    "IsController": true,
    "Order": 0,
    "Parameters": [
      {
        "Name": "id",
        "Type": "System.Int32",
        "IsRequired": true
      }
    ],
    "ReturnTypes": [
      {
        "Type": "LibrarySystemApi.Dtos.ReservationDto",
        "MediaTypes": [
          "text/plain",
          "application/json",
          "text/json"
        ],
        "StatusCode": 200
      }
    ]
  },
  {
    "ContainingType": "LibrarySystemApi.Controllers.ReservationController",
    "Method": "DeleteReservation",
    "RelativePath": "api/Reservation/{id}",
    "HttpMethod": "DELETE",
    "IsController": true,
    "Order": 0,
    "Parameters": [
      {
        "Name": "id",
        "Type": "System.Int32",
        "IsRequired": true
      }
    ],
    "ReturnTypes": []
  },
  {
    "ContainingType": "LibrarySystemApi.Controllers.ReservationController",
    "Method": "CleanupExpiredReservations",
    "RelativePath": "api/Reservation/cleanup",
    "HttpMethod": "POST",
    "IsController": true,
    "Order": 0,
    "Parameters": [],
    "ReturnTypes": []
  }
]